KratosMultiphysics/RomApplication/__init__.py
KratosMultiphysics/RomApplication/auxiliary_functions_workflow.py
KratosMultiphysics/RomApplication/calculate_rom_basis_output_process.py
KratosMultiphysics/RomApplication/empirical_cubature_method.py
KratosMultiphysics/RomApplication/hrom_training_utility.py
KratosMultiphysics/RomApplication/parallel_svd.py
KratosMultiphysics/RomApplication/petrov_galerkin_training_utility.py
KratosMultiphysics/RomApplication/python_solvers_wrapper_rom.py
KratosMultiphysics/RomApplication/randomized_singular_value_decomposition.py
KratosMultiphysics/RomApplication/rom_analysis.py
KratosMultiphysics/RomApplication/rom_database.py
KratosMultiphysics/RomApplication/rom_manager.py
KratosMultiphysics/RomApplication/rom_nn_interface.py
KratosMultiphysics/RomApplication/rom_nn_trainer.py
KratosMultiphysics/RomApplication/rom_solver.py
KratosMultiphysics/RomApplication/rom_testing_utilities.py
KratosMultiphysics/RomApplication/save_rom_coefficients_process.py
KratosMultiphysics/RomApplication/tsqr.py
KratosMultiphysics/.libs/KratosRomApplication.pyd
KratosMultiphysics/.libs/KratosRomCore.dll
KratosMultiphysics/.libs/KratosRomCore.lib
kratosromapplication-10.4.0.dist-info/METADATA
kratosromapplication-10.4.0.dist-info/WHEEL
kratosromapplication-10.4.0.dist-info/RECORD
